pyCamSet/__init__.py
pyCamSet/calibration/__init__.py
pyCamSet/calibration/camera_calibrator.py
pyCamSet/calibration_targets/__init__.py
pyCamSet/calibration_targets/abstract_target.py
pyCamSet/calibration_targets/net_maker.py
pyCamSet/calibration_targets/shape_by_faces.py
pyCamSet/calibration_targets/target_Ccube.py
pyCamSet/calibration_targets/target_charuco.py
pyCamSet/calibration_targets/target_detections.py
pyCamSet/cameras/__init__.py
pyCamSet/cameras/camera.py
pyCamSet/cameras/camera_set.py
pyCamSet/optimisation/__init__.py
pyCamSet/optimisation/abstract_function_blocks.py
pyCamSet/optimisation/compiled_helpers.py
pyCamSet/optimisation/find_target.py
pyCamSet/optimisation/free_point_handler.py
pyCamSet/optimisation/function_block_implementations.py
pyCamSet/optimisation/matmul_map.py
pyCamSet/optimisation/optimisation_handling.py
pyCamSet/optimisation/standard_bundle_handler.py
pyCamSet/optimisation/template_handler.py
pyCamSet/optimisation/template_functions/__init__.py
pyCamSet/reconstruction/__init__.py
pyCamSet/reconstruction/acmmp_utils.py
pyCamSet/reconstruction/reconstruction_utils.py
pyCamSet/utils/__init__.py
pyCamSet/utils/general_utils.py
pyCamSet/utils/saving.py
pyCamSet/utils/visualisation.py
pycamset-1.1.2.dist-info/licenses/LICENSE
pycamset-1.1.2.dist-info/METADATA
pycamset-1.1.2.dist-info/WHEEL
pycamset-1.1.2.dist-info/top_level.txt
pycamset-1.1.2.dist-info/RECORD
