Metadata-Version: 2.4
Name: pyCamSet
Version: 1.1.2
Summary: Object oriented cameras for computer vision
Home-page: https://github.com/rlav440/pyCamSet
Author: Robin Laven
Author-email: r.laven@auckland.ac.nz
License: "Apache-2.0"
Requires-Python: >=3.11
License-File: LICENSE
Requires-Dist: numpy
Requires-Dist: pyvista
Requires-Dist: scipy
Requires-Dist: matplotlib
Requires-Dist: opencv-python
Requires-Dist: tqdm
Requires-Dist: numba
Requires-Dist: natsort
Requires-Dist: coloredlogs
Requires-Dist: blosc
Requires-Dist: uniplot
Requires-Dist: scikit-learn
Requires-Dist: dill
Dynamic: license-file
